jupyter_keepalive/__init__.py
jupyter_keepalive/handlers.py
jupyter_keepalive/labextension/build_log.json
jupyter_keepalive/labextension/package.json
jupyter_keepalive/labextension/static/lib_index_js.969879db0425465fe6ea.js
jupyter_keepalive/labextension/static/lib_index_js.969879db0425465fe6ea.js.map
jupyter_keepalive/labextension/static/remoteEntry.93b38f925ef90f3c4b5a.js
jupyter_keepalive/labextension/static/remoteEntry.93b38f925ef90f3c4b5a.js.map
jupyter_keepalive/labextension/static/style.js
jupyter_keepalive-0.3.0.data/data/etc/jupyter/jupyter_server_config.d/jupyter_keepalive.json
jupyter_keepalive-0.3.0.data/data/share/jupyter/labextensions/@minrk/jupyter-keepalive/build_log.json
jupyter_keepalive-0.3.0.data/data/share/jupyter/labextensions/@minrk/jupyter-keepalive/package.json
jupyter_keepalive-0.3.0.data/data/share/jupyter/labextensions/@minrk/jupyter-keepalive/static/lib_index_js.969879db0425465fe6ea.js
jupyter_keepalive-0.3.0.data/data/share/jupyter/labextensions/@minrk/jupyter-keepalive/static/lib_index_js.969879db0425465fe6ea.js.map
jupyter_keepalive-0.3.0.data/data/share/jupyter/labextensions/@minrk/jupyter-keepalive/static/remoteEntry.93b38f925ef90f3c4b5a.js
jupyter_keepalive-0.3.0.data/data/share/jupyter/labextensions/@minrk/jupyter-keepalive/static/remoteEntry.93b38f925ef90f3c4b5a.js.map
jupyter_keepalive-0.3.0.data/data/share/jupyter/labextensions/@minrk/jupyter-keepalive/static/style.js
jupyter_keepalive-0.3.0.dist-info/METADATA
jupyter_keepalive-0.3.0.dist-info/WHEEL
jupyter_keepalive-0.3.0.dist-info/licenses/LICENSE
jupyter_keepalive-0.3.0.dist-info/RECORD
