Metadata-Version: 2.3
Name: jupyter-keepalive
Version: 0.3.0
Summary: keep jupyter servers alive while you walk away
Project-URL: Documentation, https://github.com/minrk/jupyter-keepalive#readme
Project-URL: Issues, https://github.com/minrk/jupyter-keepalive/issues
Project-URL: Source, https://github.com/minrk/jupyter-keepalive
Author-email: Min RK <benjaminrk@gmail.com>
License-Expression: BSD-3-Clause
License-File: LICENSE
Classifier: Development Status :: 4 - Beta
Classifier: Programming Language :: Python
Classifier: Programming Language :: Python :: 3.7
Classifier: Programming Language :: Python :: 3.8
Classifier: Programming Language :: Python :: 3.9
Classifier: Programming Language :: Python :: 3.10
Classifier: Programming Language :: Python :: 3.11
Classifier: Programming Language :: Python :: Implementation :: CPython
Classifier: Programming Language :: Python :: Implementation :: PyPy
Requires-Python: >=3.7
Requires-Dist: jupyter-server
Provides-Extra: test
Requires-Dist: jupyter-server[test]; extra == 'test'
Requires-Dist: pytest; extra == 'test'
Requires-Dist: pytest-asyncio; extra == 'test'
Requires-Dist: pytest-cov; extra == 'test'
